djhtml/__init__.py
djhtml/__main__.py
djhtml/lines.py
djhtml/modes.py
djhtml/options.py
djhtml/tokens.py
djhtml-3.0.9.dist-info/licenses/LICENSE
djhtml-3.0.9.dist-info/METADATA
djhtml-3.0.9.dist-info/WHEEL
djhtml-3.0.9.dist-info/entry_points.txt
djhtml-3.0.9.dist-info/top_level.txt
djhtml-3.0.9.dist-info/RECORD
