Metadata-Version: 2.4
Name: djhtml
Version: 3.0.9
Summary: Django/Jinja template indenter
Home-page: https://github.com/rtts/djhtml
Author: Jaap Joris Vens
Author-email: jj@rtts.eu
License: GPLv3+
Classifier: Programming Language :: Python :: 3
Classifier: Programming Language :: Python :: 3 :: Only
Classifier: Programming Language :: Python :: 3.9
Classifier: Programming Language :: Python :: 3.10
Classifier: Programming Language :: Python :: 3.11
Classifier: Programming Language :: Python :: 3.12
Classifier: Programming Language :: Python :: 3.13
Classifier: License :: OSI Approved :: GNU General Public License v3 or later (GPLv3+)
Classifier: Operating System :: OS Independent
License-File: LICENSE
Provides-Extra: dev
Requires-Dist: nox; extra == "dev"
Requires-Dist: pre-commit; extra == "dev"
Dynamic: license-file
